<ui:UiBinder xmlns:ui='urn:ui:com.google.gwt.uibinder'
             xmlns:design="urn:import:gwt.material.design.client.ui"
             xmlns:views="urn:import:com.geocento.webapps.eobroker.customer.client.views"
             xmlns:g="urn:import:com.google.gwt.user.client.ui"
        >
    <ui:style>
        .panel {
            max-width: 960px;
            margin: 0px auto;
            padding: 0px 20px;
        }
    </ui:style>
    <g:HTMLPanel addStyleNames="{style.panel}">
        <design:MaterialTitle title="Manage your requests" description="Here are all your currently opened requests"></design:MaterialTitle>
        <design:MaterialRow ui:field="requestsList"></design:MaterialRow>
    </g:HTMLPanel>
</ui:UiBinder>
