<ui:UiBinder xmlns:ui='urn:ui:com.google.gwt.uibinder'
             xmlns:design="urn:import:gwt.material.design.client.ui"
             xmlns:widgets="urn:import:com.geocento.webapps.eobroker.common.client.widgets"
        >
    <ui:style>

        .description {
            overflow: hidden;
            line-height: 1.2em;
            height: 2.4em;
            /* TODO - find something more cross browser */
            -webkit-line-clamp: 2;
            display: -webkit-box;
            -webkit-box-orient: vertical;
            color: #ccc;
        }

        .stars > i {
            margin-right: 5px !important;
        }

        .image {
            cursor: pointer;
        }

        .title {
            overflow: hidden;
            white-space: nowrap;
            text-overflow: ellipsis;
        }

        .follow {
            float: right;
        }

    </ui:style>
    <ui:with field="res" type="com.geocento.webapps.eobroker.common.client.styles.StyleResources"></ui:with>
    <design:MaterialCard backgroundColor="BLUE_GREY" axis="HORIZONTAL">
        <design:MaterialCardImage backgroundColor="WHITE">
            <widgets:MaterialImageLoading addStyleNames="{style.image}" ui:field="imagePanel"></widgets:MaterialImageLoading>
        </design:MaterialCardImage>
        <design:MaterialCardContent textColor="WHITE" padding="10">
            <design:MaterialLabel fontSize="1.2em" truncate="true" addStyleNames="{style.title}" ui:field="title"/>
            <design:MaterialLabel addStyleNames="{style.description}" ui:field="description"></design:MaterialLabel>
        </design:MaterialCardContent>
        <design:MaterialCardAction padding="10">
            <design:MaterialLink text="CONTACT" textColor="WHITE" ui:field="contact"></design:MaterialLink>
        </design:MaterialCardAction>
    </design:MaterialCard>
</ui:UiBinder>